{
  "slug": "bouncer-wristbands",
  "levelId": "conditionals",
  "hints": [
    {
      "question": "Hint",
      "answer": "Start by storing the age in a variable, e.g. let age = getAge()"
    },
    {
      "question": "Hint",
      "answer": "Use if/else if/else to check the age ranges in order"
    },
    {
      "question": "Hint",
      "answer": "Check the youngest group first (age < 13), then work upwards"
    },
    {
      "question": "Hint",
      "answer": "The last group (seniors) doesn't need a condition — use else"
    }
  ]
}
